database_cubic_hecke/__init__.py
database_cubic_hecke/__version__.py
database_cubic_hecke/marin_basis.py
database_cubic_hecke/marin_irred_reprs.py
database_cubic_hecke/marin_regl_reprs.py
database_cubic_hecke/marin_regr_reprs.py
database_cubic_hecke/markov_trace_coeffs.py
database_cubic_hecke/markov_trace_coeffs_irr.py
database_cubic_hecke-2022.4.4.dist-info/LICENSE
database_cubic_hecke-2022.4.4.dist-info/METADATA
database_cubic_hecke-2022.4.4.dist-info/WHEEL
database_cubic_hecke-2022.4.4.dist-info/top_level.txt
database_cubic_hecke-2022.4.4.dist-info/RECORD
