Metadata-Version: 2.1
Name: database_cubic_hecke
Version: 2022.4.4
Summary: Ivan Marin's representations of the cubic Hecke algebra on 4 strands as Python dictionaries
Home-page: https://github.com/soehms/database_cubic_hecke
Author: Sebastian Oehms
Author-email: seb.oehms@gmail.com
License: GPL
Keywords: Hecke,algebra,SageMath,database,cyclotomic,Markov,mathematics
Platform: UNKNOWN
Classifier: Development Status :: 4 - Beta
Classifier: Programming Language :: Python :: 3
License-File: LICENSE
